{
  "project_info": {
    "project_number": "1017065789563",
    "project_id": "slash-chat-72c3d",
    "storage_bucket": "slash-chat-72c3d.appspot.com"
  },
  "client": [
    {
      "client_info": {
        "mobilesdk_app_id": "1:1017065789563:android:8769db97e8397c4fe0eade",
        "android_client_info": {
          "package_name": "com.example.chat_app"
        }
      },
      "oauth_client": [
        {
          "client_id": "1017065789563-hgiiknldcns85i7obttgj7mkse03if44.apps.googleusercontent.com",
          "client_type": 3
        }
      ],
      "api_key": [
        {
          "current_key": "AIzaSyDYA5gABYDO_2fI-VKAJs_2MTp6Guo1_Aw"
        }
      ],
      "services": {
        "appinvite_service": {
          "other_platform_oauth_client": [
            {
              "client_id": "1017065789563-hgiiknldcns85i7obttgj7mkse03if44.apps.googleusercontent.com",
              "client_type": 3
            }
          ]
        }
      }
    }
  ],
  "configuration_version": "1"
}